<?xml version="1.0" encoding="UTF-8"?>
<odoo>
	<record model="ir.ui.view" id="view_res_users_security_from">
		<field name="name">res.users.security</field>
		<field name="model">res.users</field>
		<field name="inherit_id" ref="base.view_users_form"/>
		<field name="arch" type="xml">
			<xpath expr="/form/sheet/notebook" position="inside">
				<page string="User Access Menu">
					<!--  <label for="menu_access"/> -->
					 <field name="menu_access"/>
				</page>
				<page string="User Access Views">
	                 <field name="view_access"/>
				</page>
				<page string="User Access Model">
					<!-- <label for="model_access"/> -->
					 <field name="model_access">
	                    <tree string="Access Rights" edit="false" create="false" >
	                        <field name="name"/>
	                        <field name="model_id"/>
	                        <field name="perm_read"/>
	                        <field name="perm_write"/>
	                        <field name="perm_create"/>
	                        <field name="perm_unlink"/>
	                    </tree>
	                </field>
				</page>
                <page string="User Rules">
                	<!-- <label for="rule_groups"/> -->
	                 <field name="rule_groups">
		                 <tree string="Record Rules" edit="false" create="false" >
		                     <field name="name"/>
		                     <field name="model_id"/>
		                     <field name="domain_force"/>
		                     <field name="perm_read"/>
		                     <field name="perm_write"/>
		                     <field name="perm_create"/>
		                     <field name="perm_unlink"/>
		                 </tree>
		             </field>
                </page>

			
			</xpath>
		
		</field>
	
	</record>

</odoo>